half_adder.vhd
library IEEE;
use IEEE.STD_LOGIC_1164.ALL;

entity half_adder is
    port (
        A, B : in STD_LOGIC;
        Sum, Carry : out STD_LOGIC
    );
end half_adder;

architecture Behavioral of half_adder is
begin
    Sum <= A xor B;
    Carry <= A and B;
end Behavioral;

half_adder_tb.vhd
library IEEE;
use IEEE.STD_LOGIC_1164.ALL;

entity half_adder_tb is
end half_adder_tb;

architecture Behavioral of half_adder_tb is
    -- سیگنال‌های تست‌بنچ
    signal A, B, Sum, Carry : STD_LOGIC;

    -- تعریف کامپوننت نیمه‌جمع‌کننده
    component half_adder
        port (
            A, B : in STD_LOGIC;
            Sum, Carry : out STD_LOGIC
        );
    end component;

begin
    -- اتصال کامپوننت به سیگنال‌ها
    uut: half_adder port map (
        A => A,
        B => B,
        Sum => Sum,
        Carry => Carry
    );

    -- فرآیند تحریک ورودی‌ها
    stim_proc: process
    begin
        for i in 1 to 3 loop
          A <= '0'; B <= '0'; wait for 1 ns;
          A <= '0'; B <= '1'; wait for 1 ns;
          A <= '1'; B <= '0'; wait for 1 ns;
          A <= '1'; B <= '1'; wait for 1 ns;
        end loop;
        wait;
    end process;
end Behavioral;

half_adder_tb.vcd
$date
  Tue Apr 15 10:03:49 2025
$end
$version
  GHDL v0
$end
$timescale
  1 fs
$end
$scope module standard $end
$upscope $end
$scope module textio $end
$upscope $end
$scope module std_logic_1164 $end
$upscope $end
$scope module half_adder_tb $end
$var reg 1 ! a $end
$var reg 1 " b $end
$var reg 1 # sum $end
$var reg 1 $ carry $end
$scope module uut $end
$var reg 1 % a $end
$var reg 1 & b $end
$var reg 1 ' sum $end
$var reg 1 ( carry $end
$upscope $end
$upscope $end
$enddefinitions $end
#0
0!
0"
0#
0$
0%
0&
0'
0(
#1000000
1"
1#
1&
1'
#2000000
1!
0"
1%
0&
#3000000
1"
0#
1$
1&
0'
1(
#4000000
0!
0"
0$
0%
0&
0(
#5000000
1"
1#
1&
1'
#6000000
1!
0"
1%
0&
#7000000
1"
0#
1$
1&
0'
1(
#8000000
0!
0"
0$
0%
0&
0(
#9000000
1"
1#
1&
1'
#10000000
1!
0"
1%
0&
#11000000
1"
0#
1$
1&
0'
1(
